colortrans/__init__.py
colortrans/__main__.py
colortrans/colortrans.py
colortrans/version.txt
colortrans-1.1.0.dist-info/licenses/LICENSE
colortrans-1.1.0.dist-info/METADATA
colortrans-1.1.0.dist-info/WHEEL
colortrans-1.1.0.dist-info/entry_points.txt
colortrans-1.1.0.dist-info/top_level.txt
colortrans-1.1.0.dist-info/RECORD
